docker_hub-5.0.0.dist-info/licenses/LICENSE
src/__init__.py
src/__main__.py
src/consts.py
src/commands/__init__.py
src/commands/builds.py
src/commands/config.py
src/commands/login.py
src/commands/queue.py
src/commands/repos.py
src/commands/tags.py
src/commands/users.py
src/commands/version.py
src/libs/__init__.py
src/libs/config.py
src/libs/docker_client.py
src/libs/docker_hub_client.py
src/libs/utils.py
src/tests/__init__.py
src/tests/docker_hub_client.py
src/tests/helpers.py
src/tests/commands/__init__.py
src/tests/commands/test_tags.py
src/tests/commands/test_users.py
docker_hub-5.0.0.dist-info/METADATA
docker_hub-5.0.0.dist-info/WHEEL
docker_hub-5.0.0.dist-info/entry_points.txt
docker_hub-5.0.0.dist-info/top_level.txt
docker_hub-5.0.0.dist-info/RECORD
