Metadata-Version: 2.4
Name: docker-hub
Version: 5.0.0
Summary: Access docker hub from your terminal
Home-page: http://github.com/amalfra/docker-hub
Author: Amal Francis
Author-email: amalfra@gmail.com
License: MIT
Keywords: docker,cli,docker-hub,client,tools
Classifier: Development Status :: 5 - Production/Stable
Classifier: Environment :: Console
Classifier: Intended Audience :: Developers
Classifier: License :: OSI Approved :: MIT License
Classifier: Natural Language :: English
Classifier: Programming Language :: Python :: 3
Requires-Python: >=3.8
License-File: LICENSE
Requires-Dist: requests==2.28.0
Requires-Dist: tabulate==0.8.10
Requires-Dist: python-dateutil==2.8.2
Provides-Extra: test
Requires-Dist: pytest; extra == "test"
Requires-Dist: pylint; extra == "test"
Requires-Dist: coverage; extra == "test"
Requires-Dist: coveralls; extra == "test"
Dynamic: license-file
